starbug/coords.cpython-37m-darwin.so
starbug.coords-1.0.0.dist-info/LICENSE
starbug.coords-1.0.0.dist-info/METADATA
starbug.coords-1.0.0.dist-info/WHEEL
starbug.coords-1.0.0.dist-info/top_level.txt
starbug.coords-1.0.0.dist-info/RECORD
