Metadata-Version: 2.1
Name: starbug.coords
Version: 1.0.0
Summary: coords package
Home-page: https://github.com/lrmcfarland/Coordinates
Author: Lincoln Randall McFarland
Author-email: lrm@starbug.com
License: UNKNOWN
Platform: UNKNOWN
Classifier: Programming Language :: Python :: 3
Classifier: License :: OSI Approved :: MIT License
Classifier: Operating System :: OS Independent
Classifier: Topic :: Scientific/Engineering :: Astronomy
